Metadata-Version: 1.1
Name: django-nested-formsets
Version: 0.4.4
Summary: Simple nested formsets in a ModelForm
Home-page: https://bitbucket.org/ionata/django-nested-formsets
Author: Ionata Web Solutions
Author-email: webmaster@ionata.com.au
License: UNKNOWN
Platform: UNKNOWN
Classifier: Environment :: Web Environment
Classifier: Intended Audience :: Developers
Classifier: Operating System :: OS Independent
Classifier: Programming Language :: Python
Classifier: Framework :: Django
